idfva/__init__.py
idfva/_version.py
idfva/apply_modified_voronoi.py
idfva/estimate_volume_and_plot.py
idfva/generate_query_points.py
idfva/las2ras.py
idfva/prepare_path.py
idfva/process_watersheds.py
idfva/py.typed
idfva-0.1.2.dist-info/METADATA
idfva-0.1.2.dist-info/WHEEL
idfva-0.1.2.dist-info/licenses/LICENSE
idfva-0.1.2.dist-info/RECORD
